mcot/__init__.py
mcot/gcoord/README.rst
mcot/gcoord/VERSION
mcot/gcoord/__init__.py
mcot/gcoord/orientation.py
mcot/gcoord/radial_transition.py
mcot/gcoord/_scripts/__init__.py
mcot/gcoord/_scripts/gcoord/__init__.py
mcot/gcoord/_scripts/gcoord/gen.py
mcot/gcoord/_scripts/gcoord/gui.py
mcot/gcoord/_scripts/gcoord/mult.py
mcot/gcoord/_scripts/gcoord/split.py
mcot/gcoord/_scripts/gcoord/transition.py
mcot.gcoord-0.1.1.dist-info/METADATA
mcot.gcoord-0.1.1.dist-info/WHEEL
mcot.gcoord-0.1.1.dist-info/namespace_packages.txt
mcot.gcoord-0.1.1.dist-info/top_level.txt
mcot.gcoord-0.1.1.dist-info/RECORD
